arcticdb_ext.cpython-311-darwin.so
arcticc/__init__.py
arcticc/pb2/__init__.py
arcticdb/options.py
arcticdb/config.py
arcticdb/log.py
arcticdb/tools.py
arcticdb/__init__.py
arcticdb/arctic.py
arcticdb/supported_types.py
arcticdb/file.py
arcticdb/encoding_version.py
arcticdb/exceptions.py
arcticdb/flattener.py
arcticdb/_msgpack_compat.py
arcticdb/preconditions.py
arcticdb/dependencies.py
arcticdb/proto/6/arcticc/pb2/mapped_file_storage_pb2.py
arcticdb/proto/6/arcticc/pb2/utils_pb2.py
arcticdb/proto/6/arcticc/pb2/descriptors_pb2.py
arcticdb/proto/6/arcticc/pb2/logger_pb2.py
arcticdb/proto/6/arcticc/pb2/lmdb_storage_pb2.py
arcticdb/proto/6/arcticc/pb2/s3_storage_pb2.py
arcticdb/proto/6/arcticc/pb2/in_memory_storage_pb2.py
arcticdb/proto/6/arcticc/pb2/encoding_pb2.py
arcticdb/proto/6/arcticc/pb2/nfs_backed_storage_pb2.py
arcticdb/proto/6/arcticc/pb2/config_pb2.py
arcticdb/proto/6/arcticc/pb2/azure_storage_pb2.py
arcticdb/proto/6/arcticc/pb2/mongo_storage_pb2.py
arcticdb/proto/6/arcticc/pb2/gcp_storage_pb2.py
arcticdb/proto/6/arcticc/pb2/storage_pb2.py
arcticdb/proto/4/arcticc/pb2/mapped_file_storage_pb2.py
arcticdb/proto/4/arcticc/pb2/utils_pb2.py
arcticdb/proto/4/arcticc/pb2/descriptors_pb2.py
arcticdb/proto/4/arcticc/pb2/logger_pb2.py
arcticdb/proto/4/arcticc/pb2/lmdb_storage_pb2.py
arcticdb/proto/4/arcticc/pb2/s3_storage_pb2.py
arcticdb/proto/4/arcticc/pb2/in_memory_storage_pb2.py
arcticdb/proto/4/arcticc/pb2/encoding_pb2.py
arcticdb/proto/4/arcticc/pb2/nfs_backed_storage_pb2.py
arcticdb/proto/4/arcticc/pb2/config_pb2.py
arcticdb/proto/4/arcticc/pb2/azure_storage_pb2.py
arcticdb/proto/4/arcticc/pb2/mongo_storage_pb2.py
arcticdb/proto/4/arcticc/pb2/gcp_storage_pb2.py
arcticdb/proto/4/arcticc/pb2/storage_pb2.py
arcticdb/proto/5/arcticc/pb2/mapped_file_storage_pb2.py
arcticdb/proto/5/arcticc/pb2/utils_pb2.py
arcticdb/proto/5/arcticc/pb2/descriptors_pb2.py
arcticdb/proto/5/arcticc/pb2/logger_pb2.py
arcticdb-6.5.0.dist-info/RECORD
arcticdb-6.5.0.dist-info/WHEEL
arcticdb-6.5.0.dist-info/entry_points.txt
arcticdb-6.5.0.dist-info/top_level.txt
arcticdb-6.5.0.dist-info/METADATA
arcticdb-6.5.0.dist-info/licenses/NOTICE.txt
arcticdb-6.5.0.dist-info/licenses/LICENSE.txt
