Metadata-Version: 2.4
Name: arcticdb
Version: 6.5.0
Summary: ArcticDB DataFrame Database
Home-page: https://github.com/man-group/arcticdb
Author: Man Alpha Technology
Author-email: info@arcticdb.io
License: Business Source License 1.1 (See LICENSE.txt)
Classifier: Programming Language :: Python :: 3
Classifier: Operating System :: POSIX :: Linux
Classifier: Operating System :: Microsoft :: Windows
Classifier: Operating System :: MacOS
Classifier: Topic :: Database
Classifier: Topic :: Database :: Database Engines/Servers
License-File: LICENSE.txt
License-File: NOTICE.txt
Requires-Dist: pandas
Requires-Dist: numpy
Requires-Dist: attrs
Requires-Dist: protobuf<7,>=3.5.0.post1
Requires-Dist: msgpack>=0.5.0
Requires-Dist: pyyaml
Requires-Dist: packaging
Provides-Extra: arrow
Requires-Dist: polars; extra == "arrow"
Requires-Dist: pyarrow; extra == "arrow"
Provides-Extra: testing
Requires-Dist: pytest; extra == "testing"
Requires-Dist: polars; extra == "testing"
Requires-Dist: pyarrow; extra == "testing"
Requires-Dist: pytest-cpp; extra == "testing"
Requires-Dist: pytest-timeout; extra == "testing"
Requires-Dist: pytest-xdist; extra == "testing"
Requires-Dist: packaging; extra == "testing"
Requires-Dist: future; extra == "testing"
Requires-Dist: mock; extra == "testing"
Requires-Dist: boto3; extra == "testing"
Requires-Dist: moto; extra == "testing"
Requires-Dist: flask; extra == "testing"
Requires-Dist: flask-cors; extra == "testing"
Requires-Dist: hypothesis<6.73; extra == "testing"
Requires-Dist: azure-storage-blob; extra == "testing"
Requires-Dist: azure-identity; extra == "testing"
Requires-Dist: coverage; extra == "testing"
Requires-Dist: asv; (platform_system == "Linux" or python_version < "3.13") and extra == "testing"
Requires-Dist: virtualenv; extra == "testing"
Requires-Dist: pymongo; extra == "testing"
Requires-Dist: trustme; extra == "testing"
Requires-Dist: psutil; extra == "testing"
Requires-Dist: retrying; extra == "testing"
Dynamic: description
Dynamic: description-content-type
Dynamic: license-file
